git_workflow/__about__.py
git_workflow/__init__.py
git_workflow/__main__.py
git_workflow/utils/__init__.py
git_workflow/utils/cmd.py
git_workflow/utils/configs.py
git_workflow/utils/files.py
git_workflow/utils/parser.py
git_workflow/utils/repository.py
git_workflow/workflow/__init__.py
git_workflow/workflow/base.py
git_workflow/workflow/cleanup.py
git_workflow/workflow/finish_branch.py
git_workflow/workflow/set_template.py
git_workflow/workflow/start_branch.py
git_workflow/workflow/unset_template.py
git_workflow-0.3.0.dist-info/LICENSE
git_workflow-0.3.0.dist-info/METADATA
git_workflow-0.3.0.dist-info/WHEEL
git_workflow-0.3.0.dist-info/entry_points.txt
git_workflow-0.3.0.dist-info/top_level.txt
git_workflow-0.3.0.dist-info/RECORD
