Metadata-Version: 2.1
Name: git-workflow
Version: 0.3.0
Summary: Utilities for streamlining our git workflow.
Home-page: https://github.com/connordelacruz/git-workflow
Author: Connor de la Cruz
Author-email: connor.c.delacruz@gmail.com
License: MIT
Platform: UNKNOWN
Classifier: Programming Language :: Python :: 3
Classifier: Programming Language :: Python :: 3.6
Classifier: Programming Language :: Python :: 3.7
Classifier: Programming Language :: Python :: 3.8
Classifier: Programming Language :: Python :: 3.9
Classifier: Programming Language :: Python :: 3.10
Classifier: License :: OSI Approved :: MIT License
Classifier: Operating System :: OS Independent
Classifier: Environment :: Console
Classifier: Environment :: Console :: Curses
Classifier: Topic :: Software Development :: Version Control :: Git
Classifier: Topic :: Software Development
Classifier: Development Status :: 4 - Beta
Requires-Python: >=3.6
Requires-Dist: GitPython (==3.1.11)
Requires-Dist: cmd-utils (<1.1,>=1.0.0)
Requires-Dist: argcomplete (<1.13,>=1.12)
Provides-Extra: dev
Requires-Dist: Jinja2 (<2.12,>=2.11) ; extra == 'dev'
Requires-Dist: build ; extra == 'dev'
Requires-Dist: vermin ; extra == 'dev'
